gpuniq/__init__.py
gpuniq-1.0.5.dist-info/METADATA
gpuniq-1.0.5.dist-info/WHEEL
gpuniq-1.0.5.dist-info/top_level.txt
gpuniq-1.0.5.dist-info/RECORD
