Metadata-Version: 2.4
Name: GPUniq
Version: 1.0.5
Summary: Python client for GPUniq LLM API
Author-email: Egor Kalinin <kalinin-egor@users.noreply.github.com>
Project-URL: Homepage, https://github.com/GPUniq/GPUniq
Project-URL: Repository, https://github.com/GPUniq/GPUniq
Classifier: Programming Language :: Python :: 3
Classifier: License :: OSI Approved :: MIT License
Classifier: Operating System :: OS Independent
Requires-Python: >=3.7
Requires-Dist: requests>=2.25.0
